notedlib/__init__.py
notedlib/__main__.py
notedlib/api.py
notedlib/config.py
notedlib/console.py
notedlib/database.py
notedlib/encryption_service.py
notedlib/exception.py
notedlib/logging.py
notedlib/migration.py
notedlib/noted.py
notedlib/prompt.py
notedlib/storage.py
notedlib/subscribable_dict.py
notedlib/test_subscribable_dict.py
notedlib/file_vault/__init__.py
notedlib/file_vault/file_vault_service.py
notedlib/file_vault/protected_file.py
notedlib/file_vault/protected_file_cryptor.py
notedlib/file_vault/test_file_vault_service.py
notedlib/helper/__init__.py
notedlib/helper/cli.py
notedlib/helper/database.py
notedlib/helper/date.py
notedlib/helper/encryption.py
notedlib/helper/search.py
notedlib/helper/string.py
notedlib/helper/test_search.py
notedlib/helper/test_string.py
notedlib/helper/validation.py
notedlib/model/__init__.py
notedlib/model/base.py
notedlib/model/note.py
notedlib/model/note_list_result.py
notedlib/model/note_tag.py
notedlib/model/tag.py
notedlib/model/tag_list_result.py
notedlib/output/__init__.py
notedlib/output/output.py
notedlib/repository/__init__.py
notedlib/repository/migration.py
notedlib/repository/note.py
notedlib/repository/tag.py
notedlib/tui/__init__.py
notedlib/tui/color.py
notedlib/tui/editor.py
notedlib/tui/input.py
notedlib/tui/keymap.py
notedlib/tui/render_helper.py
notedlib/tui/state_container.py
notedlib/tui/symbol.py
notedlib/tui/test_input.py
notedlib/tui/test_keymap.py
notedlib/tui/test_render_helper.py
notedlib/tui/test_state_container.py
notedlib/tui/tui.py
notedlib/tui/view.py
notedlib/tui/components/__init__.py
notedlib/tui/components/base.py
notedlib/tui/components/confirm_bar.py
notedlib/tui/components/note_list.py
notedlib/tui/components/status_bar.py
notedlib/tui/components/title_bar.py
notedlib/tui/modes/__init__.py
notedlib/tui/modes/add_tag.py
notedlib/tui/modes/confirm_delete_note.py
notedlib/tui/modes/mode_base.py
notedlib/tui/modes/normal.py
notedlib/tui/modes/search.py
notedlib/tui/modes/tag.py
noted_cli-0.2.0.dist-info/LICENCE
noted_cli-0.2.0.dist-info/METADATA
noted_cli-0.2.0.dist-info/WHEEL
noted_cli-0.2.0.dist-info/entry_points.txt
noted_cli-0.2.0.dist-info/top_level.txt
noted_cli-0.2.0.dist-info/RECORD
