Metadata-Version: 2.1
Name: noted-cli
Version: 0.2.0
Summary: A VIM-inspired note manager for the console
Home-page: https://bitbucket.org/zappen999/noted-cli
Author: Johan Kanefur
Author-email: johan.canefur@gmail.com
License: GNU General Public License v2 (GPLv2)
Platform: any
Requires-Dist: pycrypto (==2.6.1)
